sampo/__init__.py
sampo/api/__init__.py
sampo/api/const.py
sampo/api/genetic_api.py
sampo/backend/__init__.py
sampo/backend/default.py
sampo/backend/multiproc.py
sampo/base.py
sampo/generator/__init__.py
sampo/generator/base.py
sampo/generator/config/__init__.py
sampo/generator/config/gen_counts.py
sampo/generator/config/worker_req.py
sampo/generator/environment/__init__.py
sampo/generator/environment/contractor.py
sampo/generator/environment/contractor_by_wg.py
sampo/generator/environment/landscape.py
sampo/generator/pipeline/__init__.py
sampo/generator/pipeline/cluster.py
sampo/generator/pipeline/extension.py
sampo/generator/pipeline/project.py
sampo/hybrid/__init__.py
sampo/hybrid/cycle.py
sampo/hybrid/population.py
sampo/landscape_config/__init__.py
sampo/landscape_config/material_request.py
sampo/landscape_config/road_workload.py
sampo/native/basic_types.h
sampo/native/chromosome_evaluator.cpp
sampo/native/chromosome_evaluator.h
sampo/native/CMakeLists.txt
sampo/native/contractor.h
sampo/native/dtime.cpp
sampo/native/dtime.h
sampo/native/evaluator_types.h
sampo/native/external.h
sampo/native/genetic.h
sampo/native/native.cpp
sampo/native/native.h
sampo/native/pycodec.h
sampo/native/python_deserializer.cpp
sampo/native/python_deserializer.h
sampo/native/recompile.bat
sampo/native/setup.py
sampo/native/time_estimator.cpp
sampo/native/time_estimator.h
sampo/native/timeEstimatorLibrary/IDLLoader.h
sampo/native/timeEstimatorLibrary/Unix/DLLoader.h
sampo/native/timeEstimatorLibrary/Windows/DLLoader.h
sampo/native/utils/use_numpy.cpp
sampo/native/utils/use_numpy.h
sampo/native/workgraph.h
sampo/pipeline/__init__.py
sampo/pipeline/base.py
sampo/pipeline/default.py
sampo/pipeline/delegating.py
sampo/pipeline/lag_optimization.py
sampo/pipeline/preparation.py
sampo/scheduler/__init__.py
sampo/scheduler/base.py
sampo/scheduler/generic.py
sampo/scheduler/genetic/__init__.py
sampo/scheduler/genetic/base.py
sampo/scheduler/genetic/converter.py
sampo-0.1.2.0.6.dist-info/licenses/LICENSE
sampo-0.1.2.0.6.dist-info/METADATA
sampo-0.1.2.0.6.dist-info/WHEEL
sampo-0.1.2.0.6.dist-info/RECORD
